modular_towers/__init__.py
modular_towers/core/__init__.py
modular_towers/core/core.py
modular_towers/core/utils.py
modular_towers/core/tests/__init__.py
modular_towers/core/tests/test_core.py
modular_towers/prelims/__init__.py
modular_towers/prelims/gcd.py
modular_towers/testing/__init__.py
modular_towers/testing/benchmark.py
modular_towers/testing/utils.py
modular_towers-0.1.4.dist-info/LICENSE
modular_towers-0.1.4.dist-info/METADATA
modular_towers-0.1.4.dist-info/WHEEL
modular_towers-0.1.4.dist-info/top_level.txt
modular_towers-0.1.4.dist-info/RECORD
