Metadata-Version: 2.1
Name: modular-towers
Version: 0.1.4
Summary: An algorithm that computes modular nested exponents (or towers) efficiently.
Home-page: https://github.com/avivbrook/modular-towers
Author: Aviv Brook
Author-email: avbrook@ucsc.edu
License: UNKNOWN
Project-URL: Bug Tracker, https://github.com/avivbrook/modular-towers/issues
Project-URL: CI, https://github.com/avivbrook/modular-towers/actions
Project-URL: Changelog, https://github.com/avivbrook/modular-towers/blob/master/CHANGELOG.md
Keywords: modular exponentiation,nested exponentiation
Platform: any
Classifier: Framework :: Jupyter
Classifier: Topic :: Education
Classifier: Topic :: Scientific/Engineering
Classifier: Topic :: Scientific/Engineering :: Mathematics
Classifier: Topic :: Software Development :: Libraries :: Python Modules
Classifier: Development Status :: 4 - Beta
Classifier: License :: OSI Approved :: GNU General Public License v3 or later (GPLv3+)
Classifier: Programming Language :: Python
Classifier: Programming Language :: Python :: 3
Classifier: Programming Language :: Python :: 3 :: Only
Classifier: Programming Language :: Python :: 3.6
Classifier: Programming Language :: Python :: 3.7
Classifier: Programming Language :: Python :: 3.8
Classifier: Programming Language :: Python :: 3.9
Classifier: Programming Language :: Python :: Implementation :: CPython
Classifier: Operating System :: OS Independent
Classifier: Intended Audience :: Developers
Classifier: Intended Audience :: Education
Classifier: Intended Audience :: Information Technology
Classifier: Intended Audience :: Science/Research
Requires-Python: >=3.6
Requires-Dist: sympy
